spparser/AsyncReader.py
spparser/AsyncTransformer.py
spparser/AsyncWriter.py
spparser/Extractor.py
spparser/Parser.py
spparser/Reader.py
spparser/Writer.py
spparser/__init__.py
spparser/css/CssUtils.py
spparser/css/__init__.py
spparser/csv/__init__.py
spparser/json/__init__.py
spparser/regex/RegexUtils.py
spparser/regex/__init__.py
spparser/utils/DefaultValues.py
spparser/utils/Exceptions.py
spparser/utils/__init__.py
spparser/utils/retObjects.py
spparser/xpath/XpathUtils.py
spparser/xpath/__init__.py
spparser-0.5.10.dist-info/METADATA
spparser-0.5.10.dist-info/WHEEL
spparser-0.5.10.dist-info/top_level.txt
spparser-0.5.10.dist-info/RECORD
