Metadata-Version: 2.1
Name: spparser
Version: 0.5.10
Summary: ETL tools
Home-page: https://github.com/taojinmin/spparser
Author: taojinmin
Author-email: taojinmin1996@foxmail.com
License: UNKNOWN
Platform: UNKNOWN
Classifier: Programming Language :: Python :: 3
Classifier: License :: OSI Approved :: GNU General Public License v3 (GPLv3)
Classifier: Operating System :: OS Independent
